pyagentx2/__init__.py
pyagentx2/agent.py
pyagentx2/network.py
pyagentx2/pdu.py
pyagentx2/sethandler.py
pyagentx2/updater.py
pyagentx2/mib/__init__.py
pyagentx2/mib/mib.py
pyagentx2/mib/mib_MySQL.py
pyagentx2/mib/mib_SQLite.py
pyagentx2-1.0.19.dist-info/LICENSE.txt
pyagentx2-1.0.19.dist-info/METADATA
pyagentx2-1.0.19.dist-info/WHEEL
pyagentx2-1.0.19.dist-info/top_level.txt
pyagentx2-1.0.19.dist-info/RECORD
