Metadata-Version: 2.1
Name: pyagentx2
Version: 1.0.19
Summary: AgentX package to extend SNMP with pure Python
Home-page: https://github.com/jslarraz/pyagentx2
Author: Jorge Sancho
Author-email: jslarraz@gmail.com
License: BSD
Keywords: snmp network agentx
Classifier: Development Status :: 4 - Beta
Classifier: License :: OSI Approved :: BSD License
Classifier: Environment :: No Input/Output (Daemon)
Classifier: Topic :: System :: Monitoring
Classifier: Topic :: System :: Networking
Classifier: Programming Language :: Python
Classifier: Intended Audience :: Developers
Classifier: Intended Audience :: Information Technology
Classifier: Intended Audience :: System Administrators
Classifier: Intended Audience :: Telecommunications Industry
License-File: LICENSE.txt
